jax_spatial/__init__.py
jax_spatial/kinematics/__init__.py
jax_spatial/kinematics/jacobian.py
jax_spatial/lie/__init__.py
jax_spatial/lie/se3.py
jax_spatial/spatial/__init__.py
jax_spatial/spatial/twist.py
jax_spatial-0.1.0.dist-info/METADATA
jax_spatial-0.1.0.dist-info/WHEEL
jax_spatial-0.1.0.dist-info/licenses/LICENSE
jax_spatial-0.1.0.dist-info/RECORD
